[
    {
        "id": "1",
        "name": "张三",
        "age": "20",
        "gender": "Male",
        "avatar": "avatar1.png",
        "text": "你好，我叫张三，他叫李四，谁叫王五？",
        "time": "2017-01-01 12:00:00",
        "img": [
            "Blog6.png",
            "Blog5.png",
            "Blog3.png",
            "Blog6.png"
        ],
        "like": "10",
        "comment": "5",
        "share": "2"
    },
    {
        "id": "2",
        "name": "李四",
        "age": "20",
        "gender": "Female",
        "avatar": "avatar2.jpg",
        "text": "大家好好好好好好！",
        "time": "2017-01-01 12:00:00",
        "img": [
            "Blog5.png",
            "Blog2.png"
        ],
        "like": "10",
        "comment": "5",
        "share": "2"
    },
    {
        "id": "5",
        "name": "王五",
        "age": "16",
        "gender": "Female",
        "avatar": "avatar5.jpg",
        "text": "大家好好啊啊啊啊啊啊啊啊！",
        "time": "2017-01-01 12:00:00",
        "img": [
            "Blog1.png"
        ],
        "like": "10",
        "comment": "5",
        "share": "2"
    },
    {
        "id": "8",
        "name": "一只鱼",
        "age": "21",
        "gender": "Female",
        "avatar": "avatar8.jpg",
        "text": "大家好好啊啊啊啊啊啊啊啊！",
        "time": "2017-01-01 12:00:00",
        "img": [
            "Blog2.png"
        ],
        "like": "10",
        "comment": "5",
        "share": "2"
    }
]